pyviews/__init__.py
pyviews/binding_node.py
pyviews/code.py
pyviews/containers.py
pyviews/pipes.py
pyviews/presenter.py
pyviews/setters.py
pyviews/binding/__init__.py
pyviews/binding/binder.py
pyviews/binding/config.py
pyviews/binding/expression.py
pyviews/binding/inject.py
pyviews/binding/inline.py
pyviews/binding/observable.py
pyviews/binding/once.py
pyviews/binding/twoways.py
pyviews/binding/tests/__init__.py
pyviews/binding/tests/binder_tests.py
pyviews/binding/tests/common.py
pyviews/binding/tests/config_tests.py
pyviews/binding/tests/expression_tests.py
pyviews/binding/tests/inject_tests.py
pyviews/binding/tests/inline_tests.py
pyviews/binding/tests/observable_tests.py
pyviews/binding/tests/once_tests.py
pyviews/binding/tests/twoways_tests.py
pyviews/core/__init__.py
pyviews/core/binding.py
pyviews/core/error.py
pyviews/core/expression.py
pyviews/core/reflection.py
pyviews/core/rendering.py
pyviews/core/xml.py
pyviews/core/tests/__init__.py
pyviews/core/tests/binding_tests.py
pyviews/core/tests/error_tests.py
pyviews/core/tests/expression_tests.py
pyviews/core/tests/reflection_tests.py
pyviews/core/tests/rendering_tests.py
pyviews/core/tests/xml_tests.py
pyviews/rendering/__init__.py
pyviews/rendering/config.py
pyviews/rendering/context.py
pyviews/rendering/pipeline.py
pyviews/rendering/views.py
pyviews/rendering/tests/__init__.py
pyviews/rendering/tests/config_tests.py
pyviews/rendering/tests/context_tests.py
pyviews/rendering/tests/pipeline_tests.py
pyviews/tests/__init__.py
pyviews/tests/binding_node_tests.py
pyviews/tests/code_tests.py
pyviews/tests/containers_tests.py
pyviews/tests/pipes_tests.py
pyviews/tests/presenter_tests.py
pyviews/tests/setters_tests.py
pyviews-4.0.0.dist-info/LICENSE
pyviews-4.0.0.dist-info/METADATA
pyviews-4.0.0.dist-info/WHEEL
pyviews-4.0.0.dist-info/top_level.txt
pyviews-4.0.0.dist-info/RECORD
