Metadata-Version: 2.1
Name: pyviews
Version: 4.0.0
Summary: Base package for xml views
Project-URL: Homepage, https://github.com/eumis/pyviews
Keywords: binding,pyviews,python,mvvm,tkviews,wxviews
Classifier: Development Status :: 5 - Production/Stable
Classifier: Intended Audience :: Developers
Classifier: Topic :: Software Development :: Libraries
Classifier: License :: OSI Approved :: MIT License
Classifier: Programming Language :: Python :: 3
Classifier: Programming Language :: Python :: 3 :: Only
Classifier: Programming Language :: Python :: 3.6
Classifier: Programming Language :: Python :: 3.7
Classifier: Programming Language :: Python :: 3.8
Classifier: Programming Language :: Python :: 3.9
Requires-Python: >=3.6
License-File: LICENSE
Requires-Dist: injectool (==3.*)
Requires-Dist: contextvars ; python_version < "3.7"
Requires-Dist: dataclasses ; python_version < "3.7"
